{
  "data": {
    "name": "dakaichi-my-number-1",
    "coverUrl": "https://cdn.statically.io/gh/Anime-Sama/IMG/img/contenu/dakaichi-my-number-1.jpg",
    "desc": "Saijou Takato est acteur depuis sa plus tendre enfance et élu depuis 5 ans 'l'homme le plus désiré'. Cependant, son règne s'arrête brutalement face à l'arrivée d'Azumaya Junta, un jeune acteur ayant débuté sa carrière 3 ans plus tôt. Takato supporte assez mal de se retrouver relégué au second rang et voit ce jeune prodige comme un ennemi. Néanmoins, suite à une soirée trop alcoolisée, Takato se retrouve dans le lit de Junta.",
    "genres": "Drame, Erotique, Romance, Yaoi",
    "update": "Aucune donnée.",
    "saisons": {
      "total": 1,
      "Saison 1": {
        "url": "saison1/vostfr",
        "eps": {
          "lec1": [
            "https://sendvid.com/embed/1ft4we1g",
            "https://sendvid.com/embed/2zqwvbuy",
            "https://sendvid.com/embed/cfkaqu18",
            "https://sendvid.com/embed/7p0vgsn6",
            "https://sendvid.com/embed/c4y30idb",
            "https://sendvid.com/embed/0ohr2jww",
            "https://sendvid.com/embed/xbyph8um",
            "https://sendvid.com/embed/6mv6ur3f",
            "https://sendvid.com/embed/mpybwk4u",
            "https://sendvid.com/embed/pmm1nzx9",
            "https://sendvid.com/embed/c8gthip3",
            "https://sendvid.com/embed/3p52ogod",
            "https://sendvid.com/embed/7f680oh5"
          ],
          "lec2": [
            "https://video.sibnet.ru/shell.php?videoid=4734384",
            "https://video.sibnet.ru/shell.php?videoid=4734387",
            "https://video.sibnet.ru/shell.php?videoid=4734388",
            "https://video.sibnet.ru/shell.php?videoid=4734390",
            "https://video.sibnet.ru/shell.php?videoid=4734392",
            "https://video.sibnet.ru/shell.php?videoid=4734394",
            "https://video.sibnet.ru/shell.php?videoid=4734396",
            "https://video.sibnet.ru/shell.php?videoid=4734398",
            "https://video.sibnet.ru/shell.php?videoid=4734399",
            "https://video.sibnet.ru/shell.php?videoid=4734401",
            "https://video.sibnet.ru/shell.php?videoid=4734403",
            "https://video.sibnet.ru/shell.php?videoid=4734405",
            "https://video.sibnet.ru/shell.php?videoid=4734406"
          ],
          "lec3": [
            "https://www.myvi.tv/embed/9boyg1od7aqwxntxfr8spsbbce",
            "https://www.myvi.tv/embed/5bmf6tcui5wrtendfwhzbpg5we",
            "https://www.myvi.tv/embed/8yymn9c3po4rjkqfhzk5i43h1h",
            "https://www.myvi.tv/embed/npa5rdqncxzwxck5j9wo5a41gy",
            "https://www.myvi.tv/embed/wn9xjahpdqarpji789utzx1kje",
            "https://www.myvi.tv/embed/gbx68qka9air9kkkzergtuqjzw",
            "https://www.myvi.tv/embed/4e7afsbermor88bht3d1p1h5yw",
            "https://www.myvi.tv/embed/hwrsku3up4twbrkjpmqsudnt5o",
            "https://www.myvi.tv/embed/5fthgsdek78rjxrx4my5pdognr",
            "https://www.myvi.tv/embed/3pbm43y3qegw3eu9xnn5zetr3h",
            "https://www.myvi.tv/embed/xw9ehp3mai7wpmzzhkjc9a31ke",
            "https://www.myvi.tv/embed/da3z9oqgcfarfr4pkbasdfqrno",
            "https://www.myvi.tv/embed/3yrups6sqp1wbxz3iboujd9egc"
          ]
        }
      }
    }
  }
}