{
  "data": {
    "name": "death-note",
    "coverUrl": "https://cdn.statically.io/gh/Anime-Sama/IMG/img/contenu/death-note.jpg",
    "desc": "Light Yagami, un jeune étudiant surdoué, ramasse un jour le \"Death Note\", un carnet tenu auparavant par un shinigami (Dieu de la mort), Ryuk, qui apparemment s'ennuyait dans son monde.\nIl suffit d'écrire le nom d'une personne dans ce carnet, et celle-ci meurt (selon certaines conditions que le shinigami expliquera à Light lors de leur rencontre).\nC'est ainsi qu'avec le \"Death Note\" entre les mains, Light décide de débarrasser la planète de tous les criminels pour en faire un monde juste, un monde parfait.\nCependant, qui est-il pour juger les gens ? Il devient donc le pire criminel recherché de toute la planète...",
    "genres": "Drame, Fantastique, Mystère, Psychologique, Surnaturel",
    "update": "Aucune donnée.",
    "saisons": {
      "total": 3,
      "Saison 1": {
        "url": "saison1/vostfr",
        "eps": {
          "lec1": [
            "https://sendvid.com/embed/wgrj3uro",
            "https://sendvid.com/embed/iv161471",
            "https://sendvid.com/embed/9gglezhw",
            "https://sendvid.com/embed/cw6trwup",
            "https://sendvid.com/embed/3tvfpyyp",
            "https://sendvid.com/embed/lce8xt3u",
            "https://sendvid.com/embed/k9evmo4y",
            "https://sendvid.com/embed/t9xzm7up",
            "https://sendvid.com/embed/kua6bea7",
            "https://sendvid.com/embed/o6uru15y",
            "https://sendvid.com/embed/ju89ia81",
            "https://sendvid.com/embed/rna5whgx",
            "https://sendvid.com/embed/ds2ji00s",
            "https://sendvid.com/embed/q5sgzpgj",
            "https://sendvid.com/embed/i03f1x95",
            "https://sendvid.com/embed/fus0fm88",
            "https://sendvid.com/embed/pewn6bx7",
            "https://sendvid.com/embed/5fccs1mr",
            "https://sendvid.com/embed/cak026ye",
            "https://sendvid.com/embed/p1z24xmj",
            "https://sendvid.com/embed/bkya8kz9",
            "https://sendvid.com/embed/6ndlh458",
            "https://sendvid.com/embed/ppxj1p0n",
            "https://sendvid.com/embed/n2rr5gvq",
            "https://sendvid.com/embed/gkncon3g",
            "https://sendvid.com/embed/zz73t9ok",
            "https://sendvid.com/embed/ie2k8543",
            "https://sendvid.com/embed/3j5i2ju0",
            "https://sendvid.com/embed/9k5j5vp3",
            "https://sendvid.com/embed/6wfjgrs4",
            "https://sendvid.com/embed/1z1a7hg7",
            "https://sendvid.com/embed/jvhcv9in",
            "https://sendvid.com/embed/jeclcfjv",
            "https://sendvid.com/embed/90ijoh9m",
            "https://sendvid.com/embed/gsxnb5xb",
            "https://sendvid.com/embed/0in7fxgs",
            "https://sendvid.com/embed/pf5bx6nj"
          ],
          "lec2": [
            "https://vidmoly.to/embed-fuketdu2syyy.html",
            "https://vidmoly.to/embed-z6pakyaq52yv.html",
            "https://vidmoly.to/embed-f59a9w8fd02s.html",
            "https://vidmoly.to/embed-flki0qgxoaio.html",
            "https://vidmoly.to/embed-glhy3mnwmzqq.html",
            "https://vidmoly.to/embed-ag9kj2lkgkjt.html",
            "https://vidmoly.to/embed-bhjw4li1oxgp.html",
            "https://vidmoly.to/embed-gxcg7rw8qkxt.html",
            "https://vidmoly.to/embed-6o4o44jncvqe.html",
            "https://vidmoly.to/embed-a00kra0govmu.html",
            "https://vidmoly.to/embed-v4yckax82irr.html",
            "https://vidmoly.to/embed-x7w7rp5323f7.html",
            "https://vidmoly.to/embed-r101ctwour65.html",
            "https://vidmoly.to/embed-xsyhah5ugjn8.html",
            "https://vidmoly.to/embed-96f1mn7adcsc.html",
            "https://vidmoly.to/embed-q7kyb6vaoyqw.html",
            "https://vidmoly.to/embed-rm0uvavb0tq2.html",
            "https://vidmoly.to/embed-jqaezph767m5.html",
            "https://vidmoly.to/embed-6k7gj95xvgm0.html",
            "https://vidmoly.to/embed-8obo489xpkze.html",
            "https://vidmoly.to/embed-p6qgnmk61w06.html",
            "https://vidmoly.to/embed-drm59kmc9ta0.html",
            "https://vidmoly.to/embed-kl3xp7gt3eoc.html",
            "https://vidmoly.to/embed-rx85vv4o0deu.html",
            "https://vidmoly.to/embed-gz6w3n22n3za.html",
            "https://vidmoly.to/embed-sq5vh6m7ls94.html",
            "https://vidmoly.to/embed-olbgb3grkbvf.html",
            "https://vidmoly.to/embed-o1tl58319v23.html",
            "https://vidmoly.to/embed-iasd9yd6zzwd.html",
            "https://vidmoly.to/embed-hlwi9esf25e7.html",
            "https://vidmoly.to/embed-bp5sp20m3zdy.html",
            "https://vidmoly.to/embed-ecoug18ce61i.html",
            "https://vidmoly.to/embed-5e3znujucbal.html",
            "https://vidmoly.to/embed-vrci1023o3s1.html",
            "https://vidmoly.to/embed-eyznvlcv3rl9.html",
            "https://vidmoly.to/embed-akoykmgnwk2s.html",
            "https://vidmoly.to/embed-148m1nrc0gms.html"
          ],
          "lec3": [
            "https://video.sibnet.ru/shell.php?videoid=4670053",
            "https://video.sibnet.ru/shell.php?videoid=4670054",
            "https://video.sibnet.ru/shell.php?videoid=4670056",
            "https://video.sibnet.ru/shell.php?videoid=4670057",
            "https://sendvid.com/embed/3tvfpyyp",
            "https://video.sibnet.ru/shell.php?videoid=4670061",
            "https://video.sibnet.ru/shell.php?videoid=4670063",
            "https://video.sibnet.ru/shell.php?videoid=4670067",
            "https://video.sibnet.ru/shell.php?videoid=4670071",
            "https://video.sibnet.ru/shell.php?videoid=4670075",
            "https://video.sibnet.ru/shell.php?videoid=4670078",
            "https://video.sibnet.ru/shell.php?videoid=4670085",
            "https://video.sibnet.ru/shell.php?videoid=4670094",
            "https://video.sibnet.ru/shell.php?videoid=4670100",
            "https://video.sibnet.ru/shell.php?videoid=4670104",
            "https://video.sibnet.ru/shell.php?videoid=4670109",
            "https://video.sibnet.ru/shell.php?videoid=4670114",
            "https://video.sibnet.ru/shell.php?videoid=4670117",
            "https://video.sibnet.ru/shell.php?videoid=4670119",
            "https://video.sibnet.ru/shell.php?videoid=4670121",
            "https://video.sibnet.ru/shell.php?videoid=4670123",
            "https://video.sibnet.ru/shell.php?videoid=4670125",
            "https://video.sibnet.ru/shell.php?videoid=4670127",
            "https://video.sibnet.ru/shell.php?videoid=4670129",
            "https://video.sibnet.ru/shell.php?videoid=4670131",
            "https://video.sibnet.ru/shell.php?videoid=4670133",
            "https://video.sibnet.ru/shell.php?videoid=4670136",
            "https://video.sibnet.ru/shell.php?videoid=4670138",
            "https://video.sibnet.ru/shell.php?videoid=4670143",
            "https://video.sibnet.ru/shell.php?videoid=4670146",
            "https://video.sibnet.ru/shell.php?videoid=4670151",
            "https://video.sibnet.ru/shell.php?videoid=4670160",
            "https://video.sibnet.ru/shell.php?videoid=4670165",
            "https://video.sibnet.ru/shell.php?videoid=4670170",
            "https://video.sibnet.ru/shell.php?videoid=4670173",
            "https://video.sibnet.ru/shell.php?videoid=4670175",
            "https://video.sibnet.ru/shell.php?videoid=4670178"
          ],
          "lec4": [
            "https://s22.anime-sama.fr/videos/Death%20Note/VOSTFR/Death_Note_01_VOSTFR.mp4",
            "https://s22.anime-sama.fr/videos/Death%20Note/VOSTFR/Death_Note_02_VOSTFR.mp4",
            "https://s22.anime-sama.fr/videos/Death%20Note/VOSTFR/Death_Note_03_VOSTFR.mp4",
            "https://s22.anime-sama.fr/videos/Death%20Note/VOSTFR/Death_Note_04_VOSTFR.mp4",
            "https://s22.anime-sama.fr/videos/Death%20Note/VOSTFR/Death_Note_05_VOSTFR.mp4",
            "https://s22.anime-sama.fr/videos/Death%20Note/VOSTFR/Death_Note_06_VOSTFR.mp4",
            "https://s22.anime-sama.fr/videos/Death%20Note/VOSTFR/Death_Note_07_VOSTFR.mp4",
            "https://s22.anime-sama.fr/videos/Death%20Note/VOSTFR/Death_Note_08_VOSTFR.mp4",
            "https://s22.anime-sama.fr/videos/Death%20Note/VOSTFR/Death_Note_09_VOSTFR.mp4",
            "https://s22.anime-sama.fr/videos/Death%20Note/VOSTFR/Death_Note_10_VOSTFR.mp4",
            "https://s22.anime-sama.fr/videos/Death%20Note/VOSTFR/Death_Note_11_VOSTFR.mp4",
            "https://s22.anime-sama.fr/videos/Death%20Note/VOSTFR/Death_Note_12_VOSTFR.mp4",
            "https://s22.anime-sama.fr/videos/Death%20Note/VOSTFR/Death_Note_13_VOSTFR.mp4",
            "https://s22.anime-sama.fr/videos/Death%20Note/VOSTFR/Death_Note_14_VOSTFR.mp4",
            "https://s22.anime-sama.fr/videos/Death%20Note/VOSTFR/Death_Note_15_VOSTFR.mp4",
            "https://s22.anime-sama.fr/videos/Death%20Note/VOSTFR/Death_Note_16_VOSTFR.mp4",
            "https://s22.anime-sama.fr/videos/Death%20Note/VOSTFR/Death_Note_17_VOSTFR.mp4",
            "https://s22.anime-sama.fr/videos/Death%20Note/VOSTFR/Death_Note_18_VOSTFR.mp4",
            "https://s22.anime-sama.fr/videos/Death%20Note/VOSTFR/Death_Note_19_VOSTFR.mp4",
            "https://s22.anime-sama.fr/videos/Death%20Note/VOSTFR/Death_Note_20_VOSTFR.mp4",
            "https://s22.anime-sama.fr/videos/Death%20Note/VOSTFR/Death_Note_21_VOSTFR.mp4",
            "https://s22.anime-sama.fr/videos/Death%20Note/VOSTFR/Death_Note_22_VOSTFR.mp4",
            "https://s22.anime-sama.fr/videos/Death%20Note/VOSTFR/Death_Note_23_VOSTFR.mp4",
            "https://s22.anime-sama.fr/videos/Death%20Note/VOSTFR/Death_Note_24_VOSTFR.mp4",
            "https://s22.anime-sama.fr/videos/Death%20Note/VOSTFR/Death_Note_25_VOSTFR.mp4",
            "https://s22.anime-sama.fr/videos/Death%20Note/VOSTFR/Death_Note_26_VOSTFR.mp4",
            "https://s22.anime-sama.fr/videos/Death%20Note/VOSTFR/Death_Note_27_VOSTFR.mp4",
            "https://s22.anime-sama.fr/videos/Death%20Note/VOSTFR/Death_Note_28_VOSTFR.mp4",
            "https://s22.anime-sama.fr/videos/Death%20Note/VOSTFR/Death_Note_29_VOSTFR.mp4",
            "https://s22.anime-sama.fr/videos/Death%20Note/VOSTFR/Death_Note_30_VOSTFR.mp4",
            "https://s22.anime-sama.fr/videos/Death%20Note/VOSTFR/Death_Note_31_VOSTFR.mp4",
            "https://s22.anime-sama.fr/videos/Death%20Note/VOSTFR/Death_Note_32_VOSTFR.mp4",
            "https://s22.anime-sama.fr/videos/Death%20Note/VOSTFR/Death_Note_33_VOSTFR.mp4",
            "https://s22.anime-sama.fr/videos/Death%20Note/VOSTFR/Death_Note_34_VOSTFR.mp4",
            "https://s22.anime-sama.fr/videos/Death%20Note/VOSTFR/Death_Note_35_VOSTFR.mp4",
            "https://s22.anime-sama.fr/videos/Death%20Note/VOSTFR/Death_Note_36_VOSTFR.mp4",
            "https://s22.anime-sama.fr/videos/Death%20Note/VOSTFR/Death_Note_37_VOSTFR.mp4"
          ]
        }
      },
      "Films": {
        "url": "film/vostfr",
        "eps": {
          "lec1": [
            "https://vk.com/video_ext.php?oid=751474887&id=456239133&hash=a5dbc9b4d01a99e4&hd=3",
            "https://vk.com/video_ext.php?oid=751474887&id=456239131&hash=7f08f69c07654178&hd=3"
          ]
        }
      },
      "Live Action": {
        "url": "film2/vostfr",
        "eps": {
          "lec1": [
            "https://www.myvi.tv/embed/4n1bmmw8434w9b73yqhmiykxxe"
          ],
          "lec2": [
            "https://video.sibnet.ru/shell.php?videoid=5027618"
          ]
        }
      }
    }
  }
}