{
  "data": {
    "name": "little-hands",
    "coverUrl": "https://cdn.statically.io/gh/Anime-Sama/IMG/img/contenu/little-hands.jpg",
    "desc": "Ishino Mikage décide d'intégrer le club de handball de son lycée, ce sports où la taille est un avantage implacable. Ce dernier est de petite taille, mais c'était sans compter sur son père, lui même star du handball.",
    "genres": "Action, School-Life, Slice-of-Life, Tournois, Sports",
    "update": "Aucune donnée.",
    "saisons": {
      "total": 0
    }
  }
}