{
  "data": {
    "name": "maria-no-danzai",
    "coverUrl": "https://cdn.statically.io/gh/Anime-Sama/IMG/img/contenu/maria-no-danzai.jpg",
    "desc": "La famille Nagare est une famille à trois d'apparence heureuse. Cependant, le fils Kiritaka cache à ses parents qu'il est cruellement harcelé à l'école. A la suite d'un tragique accident, l'amour bienveillant de sa mère, Mari, va se transformer en une force complétement incontrôlable.",
    "genres": "Webcomic, Seinen, Drame, Mature, Psychologique, School-Life, Harcèlement, Vengeance",
    "update": "Aucune donnée.",
    "saisons": {
      "total": 0
    }
  }
}