{
  "data": {
    "name": "slow-loop",
    "coverUrl": "https://cdn.statically.io/gh/Anime-Sama/IMG/img/contenu/slow-loop.jpg",
    "desc": "Hiyori est une adolescente assez peu à l'aise avec les interactions sociales. Ainsi, elle a pris l'habitude d'aller pêcher en bord de mer, une activité qu'elle pratiquait autrefois avec son défunt père, lorsqu'elle souhaite être un peu tranquille.\nUn jour, alors qu'elle pêche seule comme à son habitude, elle fait la connaissance de Koharu. Cette dernière s'intéresse rapidement à ce qu'elle fait et les deux adolescentes sympathisent autour d'un plat de sashimis. Peu après, elles découvrent qu'elles partageront bientôt plus qu'un repas, puisque le père de Koharu est le fiancé de la mère de Hiyori.",
    "genres": "Comédie, School-Life, Seinen, Slice-of-Life, Famille, Quotidien",
    "update": "Aucune donnée.",
    "saisons": {
      "total": 1,
      "Saison 1": {
        "url": "saison1/vostfr",
        "eps": {
          "lec1": [
            "https://sendvid.com/embed/zrlnynko",
            "https://sendvid.com/embed/cjk9a9z7",
            "https://sendvid.com/embed/pmca8lyo",
            "https://sendvid.com/embed/l4j2r1ui",
            "https://sendvid.com/embed/45atrjn2",
            "https://sendvid.com/embed/5qof2pvg",
            "https://sendvid.com/embed/96eeift9",
            "https://sendvid.com/embed/k0darcyq",
            "https://sendvid.com/embed/5fhefzp8",
            "https://sendvid.com/embed/9pj0hkii",
            "https://sendvid.com/embed/j6v8vtxu",
            "https://sendvid.com/embed/ie1vkfsk"
          ],
          "lec2": [
            "https://video.sibnet.ru/shell.php?videoid=4568682",
            "https://video.sibnet.ru/shell.php?videoid=4576094",
            "https://video.sibnet.ru/shell.php?videoid=4583476",
            "https://video.sibnet.ru/shell.php?videoid=4590580",
            "https://video.sibnet.ru/shell.php?videoid=4596368",
            "https://video.sibnet.ru/shell.php?videoid=4602843",
            "https://video.sibnet.ru/shell.php?videoid=4608501",
            "https://video.sibnet.ru/shell.php?videoid=4617174",
            "https://video.sibnet.ru/shell.php?videoid=4625365",
            "https://video.sibnet.ru/shell.php?videoid=4631510",
            "https://video.sibnet.ru/shell.php?videoid=4640090",
            "https://video.sibnet.ru/shell.php?videoid=4647867"
          ],
          "lec3": [
            "https://www.myvi.top/embed/8pxrrjbzo7kr5b3zxbtdowtktr",
            "https://www.myvi.top/embed/rip31rzh4spw8rctkase4nmsgw",
            "https://www.myvi.top/embed/dbrb5pbw9kyrfpbxcxixg8pe4o",
            "https://www.myvi.top/embed/wm5digwxsrhw7ex98skxj64eoy",
            "https://www.myvi.top/embed/t85sdjnnuekr7jmennrqktcabo",
            "https://www.myvi.top/embed/sm358tbf595rfyqbmuf1u79hoo",
            "https://www.myvi.top/embed/dwu35t5e7w8r8qhz6hgrm4fakh",
            "https://www.myvi.top/embed/qfw4ope8ionrdgwns5xhhpfc4c",
            "https://www.myvi.top/embed/gsco6nnnp3jrmkchmwdh3p9dcy",
            "https://www.myvi.top/embed/bqdrtt7saucwfjaktf6b96mgyy",
            "https://www.myvi.tv/embed/bne4zmow3rjr7em39qhin99snh",
            "https://www.myvi.tv/embed/xkzgxgrrgztwtg34cz9mjz4tzc"
          ]
        }
      }
    }
  }
}