{
  "data": {
    "name": "the-misfit-of-demon-king-academy",
    "coverUrl": "https://cdn.statically.io/gh/Anime-Sama/IMG/img/contenu/the-misfit-of-demon-king-academy.jpg",
    "desc": "Après 2000 ans, le seigneur démon, ayant la capacité de détruire les humains, les élémentaires et les dieux vient d'être réincarné !\n\nSuite à une longue période d'innombrables guerres et de conflits, Anos, le seigneur démon, devint fatigué et aspira\nà un monde pacifique. Il décida donc de se réincarner. Cependant, le monde dans lequel il se réincarne est trop habitué à la paix et ses habitants sont donc trop faibles.\n\nAnos décide de s'inscrire à l'Académie Maou, qui est un établissement créé pour rechercher tous les étudiants susceptibles de représenter la réincarnation du seigneur démon. Néanmoins, ses pouvoirs sont trop extraordinaires pour que ceux de l'académie puissent le juger correctement. Il est donc considéré comme un «étudiant incompatible».\n\nSous-estimé et évité par la plupart des habitants de la région, il décide de recruter Misha, une des seules personnes gentille avec lui, pour grimper au sommet de la hiérarchie des démons et ainsi récupérer son titre et statut antérieurs.",
    "genres": "Action, Comédie, Fantasy, School-Life",
    "update": "La partie 2 de la saison 2 sortira en 2024.",
    "saisons": {
      "total": 3,
      "Saison 1": {
        "url": "saison1/vostfr",
        "eps": {
          "lec1": [
            "https://sendvid.com/embed/dwwntdoa",
            "https://sendvid.com/embed/z3fl8qpi",
            "https://sendvid.com/embed/cw6qs3mj",
            "https://sendvid.com/embed/awpyqhg9",
            "https://sendvid.com/embed/9c43nj67",
            "https://sendvid.com/embed/ut4hvnn4",
            "https://sendvid.com/embed/lqjg1ewv",
            "https://sendvid.com/embed/f03pim08",
            "https://sendvid.com/embed/47bg6x6w",
            "https://sendvid.com/embed/wdbab9n6",
            "https://sendvid.com/embed/v81qql8y",
            "https://sendvid.com/embed/o5c3if0l",
            "https://sendvid.com/embed/odsk6k3t"
          ],
          "lec2": [
            "https://video.sibnet.ru/shell.php?videoid=4003075",
            "https://video.sibnet.ru/shell.php?videoid=4010624",
            "https://video.sibnet.ru/shell.php?videoid=4016009",
            "https://video.sibnet.ru/shell.php?videoid=4023193",
            "https://video.sibnet.ru/shell.php?videoid=4027570",
            "https://video.sibnet.ru/shell.php?videoid=4034672",
            "https://video.sibnet.ru/shell.php?videoid=4042260",
            "https://video.sibnet.ru/shell.php?videoid=4049783",
            "https://video.sibnet.ru/shell.php?videoid=4057565",
            "https://video.sibnet.ru/shell.php?videoid=4065442",
            "https://video.sibnet.ru/shell.php?videoid=4077259",
            "https://video.sibnet.ru/shell.php?videoid=4087630",
            "https://video.sibnet.ru/shell.php?videoid=4094234"
          ],
          "lec3": [
            "https://vidmoly.to/embed-tomsfmv94ka4.html",
            "https://vidmoly.to/embed-vrn6zdwicq6s.html",
            "https://vidmoly.to/embed-mnb99hjftpx7.html",
            "https://vidmoly.to/embed-chfx04kb3qo2.html",
            "https://vidmoly.to/embed-20r16r51kh4b.html",
            "https://vidmoly.to/embed-7vlmr8w1w38e.html",
            "https://vidmoly.to/embed-ehub8ks50ns1.html",
            "https://vidmoly.to/embed-abip0czqraxw.html",
            "https://vidmoly.to/embed-vt64jeenqu4s.html",
            "https://vidmoly.to/embed-yqfi9vcwwlgv.html",
            "https://vidmoly.to/embed-yroqgkxwmmu9.html",
            "https://vidmoly.to/embed-fe6y0ea8c710.html",
            "https://vidmoly.to/embed-xvkxxp1il06e.html"
          ]
        }
      },
      "Saison 2 Partie 1": {
        "url": "saison2-1/vostfr",
        "eps": {
          "lec1": [
            "https://video.sibnet.ru/shell.php?videoid=5001635",
            "https://video.sibnet.ru/shell.php?videoid=5009542",
            "https://video.sibnet.ru/shell.php?videoid=5015707",
            "https://video.sibnet.ru/shell.php?videoid=5024379",
            "https://video.sibnet.ru/shell.php?videoid=5031546",
            "https://video.sibnet.ru/shell.php?videoid=5039553",
            "https://sendvid.com/embed/57degwn5",
            "https://sendvid.com/embed/mxcasqpp",
            "https://video.sibnet.ru/shell.php?videoid=5240792",
            "https://video.sibnet.ru/shell.php?videoid=5248275",
            "https://video.sibnet.ru/shell.php?videoid=5254535",
            "https://sendvid.com/embed/1xc3a4ka"
          ],
          "lec2": [
            "https://vidmoly.to/embed-oezjd5cpb502.html",
            "https://vidmoly.to/embed-qf5xx1yzj8ek.html",
            "https://vidmoly.to/embed-t7c8wtcpx1nu.html",
            "https://vidmoly.to/embed-w2hzujpd2crg.html",
            "https://vidmoly.to/embed-xm8k0qyswgh7.html",
            "https://vidmoly.to/embed-rw4itggpx8cy.html",
            "https://vidmoly.to/embed-vt0fz4a90yvw.html",
            "https://vidmoly.to/embed-0t01vpejt0ko.html",
            "https://vidmoly.to/embed-i7cf2l87jhgd.html",
            "https://vidmoly.to/embed-x2l6yd644tte.html",
            "https://vidmoly.to/embed-x9guyvjqwxvj.html",
            "https://vidmoly.to/embed-hvekuxjsgmyr.html"
          ],
          "lec3": [
            "https://vk.com/video_ext.php?oid=751474887&id=456239148&hash=48e5e32c68d40760&hd=3",
            "https://vk.com/video_ext.php?oid=751474887&id=456239208&hash=70a2d944e0e6d25e&hd=3",
            "https://vk.com/video_ext.php?oid=751474887&id=456239257&hash=ced3c1ebba6bb079&hd=3",
            "https://vk.com/video_ext.php?oid=755747641&id=456239202&hash=cd18ab5073ac409e&hd=3",
            "https://vk.com/video_ext.php?oid=755747641&id=456239247&hash=8fe67587c50f9da1&hd=3",
            "https://vk.com/video_ext.php?oid=755747641&id=456239288&hash=c629df52fed4b4bb&hd=3",
            "https://video.sibnet.ru/shell.php?videoid=5230595",
            "https://video.sibnet.ru/shell.php?videoid=5235004",
            "https://vk.com/video_ext.php?oid=755747641&id=456240086&hd=3",
            "https://vk.com/video_ext.php?oid=755747641&id=456240113&hd=3",
            "https://vk.com/video_ext.php?oid=755747641&id=456240142&hd=3",
            "https://video.sibnet.ru/shell.php?videoid=5259693"
          ],
          "lec4": [
            "https://sendvid.com/embed/44etioya",
            "https://sendvid.com/embed/l40ls0ax",
            "https://sendvid.com/embed/3jjl4j3u",
            "https://sendvid.com/embed/7mwtk6f1",
            "https://sendvid.com/embed/hvghuzoz",
            "https://sendvid.com/embed/kepqcwdu",
            "https://sendvid.com/embed/57degwn5",
            "https://sendvid.com/embed/mxcasqpp",
            "https://sendvid.com/embed/lbvghlcw",
            "https://sendvid.com/embed/wvxf0u2a",
            "https://sendvid.com/embed/vluwb7vr",
            "https://sendvid.com/embed/1xc3a4ka"
          ],
          "lec5": [
            "https://s22.anime-sama.fr/videos/The%20Misfit%20of%20Demon%20King%20Academy/VOSTFR/The_Misfit_of_Demon_King_Academy_S2_1_VOSTFR.mp4",
            "https://s22.anime-sama.fr/videos/The%20Misfit%20of%20Demon%20King%20Academy/VOSTFR/The_Misfit_of_Demon_King_Academy_S2_2_VOSTFR.mp4",
            "https://s22.anime-sama.fr/videos/The%20Misfit%20of%20Demon%20King%20Academy/VOSTFR/The_Misfit_of_Demon_King_Academy_S2_3_VOSTFR.mp4",
            "https://s22.anime-sama.fr/videos/The%20Misfit%20of%20Demon%20King%20Academy/VOSTFR/The_Misfit_of_Demon_King_Academy_S2_4_VOSTFR.mp4",
            "https://s22.anime-sama.fr/videos/The%20Misfit%20of%20Demon%20King%20Academy/VOSTFR/The_Misfit_of_Demon_King_Academy_S2_5_VOSTFR.mp4",
            "https://s22.anime-sama.fr/videos/The%20Misfit%20of%20Demon%20King%20Academy/VOSTFR/The_Misfit_of_Demon_King_Academy_S2_6_VOSTFR.mp4",
            "https://s22.anime-sama.fr/videos/The%20Misfit%20of%20Demon%20King%20Academy/VOSTFR/The_Misfit_of_Demon_King_Academy_S2_7_VOSTFR.mp4",
            "https://s22.anime-sama.fr/videos/The%20Misfit%20of%20Demon%20King%20Academy/VOSTFR/The_Misfit_of_Demon_King_Academy_S2_8_VOSTFR.mp4",
            "https://s22.anime-sama.fr/videos/The%20Misfit%20of%20Demon%20King%20Academy/VOSTFR/The_Misfit_of_Demon_King_Academy_S2_9_VOSTFR.mp4",
            "https://s22.anime-sama.fr/videos/The%20Misfit%20of%20Demon%20King%20Academy/VOSTFR/The_Misfit_of_Demon_King_Academy_S2_10_VOSTFR.mp4",
            "https://s22.anime-sama.fr/videos/The%20Misfit%20of%20Demon%20King%20Academy/VOSTFR/The_Misfit_of_Demon_King_Academy_S2_11_VOSTFR.mp4",
            "https://s22.anime-sama.fr/videos/The%20Misfit%20of%20Demon%20King%20Academy/VOSTFR/The_Misfit_of_Demon_King_Academy_S2_12_VOSTFR.mp4"
          ]
        }
      },
      "Saison 2 Partie 2": {
        "url": "saison2-2/vostfr",
        "eps": {
          "lec1": [
            "https://video.sibnet.ru/shell.php?videoid=5503038",
            "https://video.sibnet.ru/shell.php?videoid=5509896",
            "https://video.sibnet.ru/shell.php?videoid=5516737",
            "https://video.sibnet.ru/shell.php?videoid=5524038",
            "https://video.sibnet.ru/shell.php?videoid=5531289",
            "https://video.sibnet.ru/shell.php?videoid=5538083",
            "https://video.sibnet.ru/shell.php?videoid=5550596",
            "https://video.sibnet.ru/shell.php?videoid=5556444",
            "https://video.sibnet.ru/shell.php?videoid=5562983",
            "https://video.sibnet.ru/shell.php?videoid=5578730",
            "https://video.sibnet.ru/shell.php?videoid=5584569",
            "https://video.sibnet.ru/shell.php?videoid=5608595"
          ],
          "lec2": [
            "https://vidmoly.to/embed-t69wk5uu90fy.html",
            "https://vidmoly.to/embed-9p46vvmhf2er.html",
            "https://vidmoly.to/embed-knp91piueli0.html",
            "https://vidmoly.to/embed-f4mm0qrb4phl.html",
            "https://vidmoly.to/embed-jhuzu4pgtapm.html",
            "https://vidmoly.to/embed-tmpex4jtfqp6.html",
            "https://vidmoly.to/embed-kw9yxqpec6gp.html",
            "https://vidmoly.to/embed-mn96y94p4lg4.html",
            "https://vidmoly.to/embed-eoezn1z5arzg.html",
            "https://vidmoly.to/embed-zcni1afy5xe5.html",
            "https://vidmoly.to/embed-b1sdgg9g2m1d.html",
            "https://vidmoly.to/embed-kvos87b68xgf.html"
          ],
          "lec3": [
            "https://sendvid.com/embed/4uvzjkrd",
            "https://sendvid.com/embed/ffrbyg2q",
            "https://sendvid.com/embed/s6bu08kj",
            "https://sendvid.com/embed/j4hn2gig",
            "https://sendvid.com/embed/6zsk16o5",
            "https://sendvid.com/embed/cw0925td",
            "https://sendvid.com/embed/n8f9ikod",
            "https://sendvid.com/embed/swn5t662",
            "https://sendvid.com/embed/85djova9",
            "https://sendvid.com/embed/gu6pxu8o",
            "https://sendvid.com/embed/yq1j907q",
            "https://sendvid.com/embed/qnt86tp4"
          ],
          "lec4": [
            "https://vk.com/video_ext.php?oid=751474887&id=456239459&hd=3",
            "https://vk.com/video_ext.php?oid=751474887&id=456239506&hd=3",
            "https://vk.com/video_ext.php?oid=751474887&id=456239548&hd=3",
            "https://vk.com/video_ext.php?oid=751474887&id=456239576&hd=3",
            "https://vk.com/video_ext.php?oid=751474887&id=456239616&hd=3",
            "https://vk.com/video_ext.php?oid=751474887&id=456239658&hd=3",
            "https://vk.com/video_ext.php?oid=751474887&id=456239714&hd=3",
            "https://vk.com/video_ext.php?oid=751474887&id=456239758&hd=3",
            "https://vk.com/video_ext.php?oid=751474887&id=456239797&hd=3",
            "https://vk.com/video_ext.php?oid=751474887&id=456239866&hd=3",
            "https://vk.com/video_ext.php?oid=751474887&id=456239884&hd=3",
            "https://vk.com/video_ext.php?oid=751474887&id=456240017&hd=3"
          ]
        }
      }
    }
  }
}